odoo/addons/l10n_es_aeat_mod390_extra_data/README.rst
odoo/addons/l10n_es_aeat_mod390_extra_data/__init__.py
odoo/addons/l10n_es_aeat_mod390_extra_data/__manifest__.py
odoo/addons/l10n_es_aeat_mod390_extra_data/data/2022/l10n_es_aeat_map_tax_line.xml
odoo/addons/l10n_es_aeat_mod390_extra_data/i18n/l10n_es_aeat_mod390_extra_data.pot
odoo/addons/l10n_es_aeat_mod390_extra_data/readme/CONTRIBUTORS.rst
odoo/addons/l10n_es_aeat_mod390_extra_data/readme/DESCRIPTION.rst
odoo/addons/l10n_es_aeat_mod390_extra_data/readme/HISTORY.rst
odoo/addons/l10n_es_aeat_mod390_extra_data/static/description/icon.png
odoo/addons/l10n_es_aeat_mod390_extra_data/static/description/index.html
odoo/addons/l10n_es_aeat_mod390_extra_data/tests/__init__.py
odoo/addons/l10n_es_aeat_mod390_extra_data/tests/test_l10n_es_aeat_mod390_extra_data.py
odoo11_addon_l10n_es_aeat_mod390_extra_data-11.0.2.0.0.dist-info/METADATA
odoo11_addon_l10n_es_aeat_mod390_extra_data-11.0.2.0.0.dist-info/WHEEL
odoo11_addon_l10n_es_aeat_mod390_extra_data-11.0.2.0.0.dist-info/top_level.txt
odoo11_addon_l10n_es_aeat_mod390_extra_data-11.0.2.0.0.dist-info/RECORD
